checking_smtp_starttls/__init__.py
checking_smtp_starttls/checking_smtp_starttls.py
checking_smtp_starttls/cli.py
checking_smtp_starttls-0.0.1.dist-info/DESCRIPTION.rst
checking_smtp_starttls-0.0.1.dist-info/METADATA
checking_smtp_starttls-0.0.1.dist-info/RECORD
checking_smtp_starttls-0.0.1.dist-info/WHEEL
checking_smtp_starttls-0.0.1.dist-info/entry_points.txt
checking_smtp_starttls-0.0.1.dist-info/metadata.json
checking_smtp_starttls-0.0.1.dist-info/top_level.txt
