Metadata-Version: 2.0
Name: checking-smtp-starttls
Version: 0.0.1
Summary: Check available TLS version and auth setting with SMTP STARTTLS
Home-page: https://github.com/dibisis/checking_smtp_starttls
Author: Goong Won, Chun
Author-email: dibisis@gmail.com
License: GNU General Public License v3
Keywords: checking_smtp_starttls
Platform: UNKNOWN
Classifier: Development Status :: 2 - Pre-Alpha
Classifier: Intended Audience :: Developers
Classifier: License :: OSI Approved :: GNU General Public License v3 (GPLv3)
Classifier: Natural Language :: English
Classifier: Programming Language :: Python :: 3
Classifier: Programming Language :: Python :: 3.4
Classifier: Programming Language :: Python :: 3.5
Classifier: Programming Language :: Python :: 3.6
Classifier: Programming Language :: Python :: 3.7
Requires-Dist: Click (>=6.0)
